couchers/__init__.py
couchers/client.py
couchers/services.py
couchers/version
couchers/certs/__init__.py
couchers/certs/isrg-root-x1.pem
couchers/certs/isrg-root-x2.pem
couchers/proto/__init__.py
couchers/proto/account_pb2.py
couchers/proto/account_pb2.pyi
couchers/proto/account_pb2_grpc.py
couchers/proto/account_pb2_grpc.pyi
couchers/proto/admin_pb2.py
couchers/proto/admin_pb2.pyi
couchers/proto/admin_pb2_grpc.py
couchers/proto/admin_pb2_grpc.pyi
couchers/proto/annotations_pb2.py
couchers/proto/annotations_pb2.pyi
couchers/proto/annotations_pb2_grpc.py
couchers/proto/annotations_pb2_grpc.pyi
couchers/proto/api_pb2.py
couchers/proto/api_pb2.pyi
couchers/proto/api_pb2_grpc.py
couchers/proto/api_pb2_grpc.pyi
couchers/proto/auth_pb2.py
couchers/proto/auth_pb2.pyi
couchers/proto/auth_pb2_grpc.py
couchers/proto/auth_pb2_grpc.pyi
couchers/proto/blocking_pb2.py
couchers/proto/blocking_pb2.pyi
couchers/proto/blocking_pb2_grpc.py
couchers/proto/blocking_pb2_grpc.pyi
couchers/proto/bugs_pb2.py
couchers/proto/bugs_pb2.pyi
couchers/proto/bugs_pb2_grpc.py
couchers/proto/bugs_pb2_grpc.pyi
couchers/proto/communities_pb2.py
couchers/proto/communities_pb2.pyi
couchers/proto/communities_pb2_grpc.py
couchers/proto/communities_pb2_grpc.pyi
couchers/proto/conversations_pb2.py
couchers/proto/conversations_pb2.pyi
couchers/proto/conversations_pb2_grpc.py
couchers/proto/conversations_pb2_grpc.pyi
couchers/proto/discussions_pb2.py
couchers/proto/discussions_pb2.pyi
couchers/proto/discussions_pb2_grpc.py
couchers/proto/discussions_pb2_grpc.pyi
couchers/proto/donations_pb2.py
couchers/proto/donations_pb2.pyi
couchers/proto/donations_pb2_grpc.py
couchers/proto/donations_pb2_grpc.pyi
couchers/proto/editor_pb2.py
couchers/proto/editor_pb2.pyi
couchers/proto/editor_pb2_grpc.py
couchers/proto/editor_pb2_grpc.pyi
couchers/proto/events_pb2.py
couchers/proto/events_pb2.pyi
couchers/proto/events_pb2_grpc.py
couchers/proto/events_pb2_grpc.pyi
couchers/proto/feature_requests_pb2.py
couchers-0.0.45.dist-info/licenses/license.md
couchers-0.0.45.dist-info/METADATA
couchers-0.0.45.dist-info/WHEEL
couchers-0.0.45.dist-info/top_level.txt
couchers-0.0.45.dist-info/RECORD
