Metadata-Version: 2.4
Name: couchers
Version: 0.0.45
Summary: Couchers.org: The next-generation couch surfing platform. Free forever. Community‑led. Non‑profit. Modern.
Home-page: https://couchers.org
Author: Couchers, Inc. and Contributors
Author-email: support@couchers.org
Project-URL: GitHub, https://github.com/Couchers-org/couchers
Project-URL: Bug Tracker, https://github.com/Couchers-org/couchers/issues
Classifier: Programming Language :: Python :: 3
Classifier: License :: OSI Approved :: MIT License
Classifier: Operating System :: OS Independent
Requires-Python: >=3.12
License-File: license.md
Requires-Dist: grpcio
Requires-Dist: protobuf
Dynamic: author
Dynamic: author-email
Dynamic: classifier
Dynamic: description
Dynamic: description-content-type
Dynamic: home-page
Dynamic: license-file
Dynamic: project-url
Dynamic: requires-dist
Dynamic: requires-python
Dynamic: summary
